odoo/addons/webcal_exporter/README.rst
odoo/addons/webcal_exporter/__init__.py
odoo/addons/webcal_exporter/__manifest__.py
odoo/addons/webcal_exporter/data/ir_actions_server_data.xml
odoo/addons/webcal_exporter/data/ir_cron_data.xml
odoo/addons/webcal_exporter/i18n/i18n.ca.po
odoo/addons/webcal_exporter/i18n/i18n.es.po
odoo/addons/webcal_exporter/models/__init__.py
odoo/addons/webcal_exporter/models/calendar_event.py
odoo/addons/webcal_exporter/models/res_users.py
odoo/addons/webcal_exporter/readme/CONFIGURE.rst
odoo/addons/webcal_exporter/readme/CONTRIBUTORS.rst
odoo/addons/webcal_exporter/readme/DESCRIPTION.rst
odoo/addons/webcal_exporter/readme/HISTORY.rst
odoo/addons/webcal_exporter/readme/USAGE.rst
odoo/addons/webcal_exporter/readme/newsfragments/.gitignore
odoo/addons/webcal_exporter/security/ir.model.access.csv
odoo/addons/webcal_exporter/static/description/index.html
odoo/addons/webcal_exporter/static/description/nextcloud.md
odoo/addons/webcal_exporter/views/res_users_view.xml
odoo14_addon_webcal_exporter-14.0.1.0.6.dist-info/METADATA
odoo14_addon_webcal_exporter-14.0.1.0.6.dist-info/WHEEL
odoo14_addon_webcal_exporter-14.0.1.0.6.dist-info/top_level.txt
odoo14_addon_webcal_exporter-14.0.1.0.6.dist-info/RECORD
