Metadata-Version: 2.1
Name: odoo14-addon-webcal-exporter
Version: 14.0.1.0.6
Summary: Export Odoo calendar events to external webcal
Home-page: https://coopdevs.org
Author: Coopdevs
License: AGPL-3
Classifier: Programming Language :: Python
Classifier: Framework :: Odoo
Classifier: Framework :: Odoo :: 14.0
Classifier: License :: OSI Approved :: GNU Affero General Public License v3
Requires-Python: >=3.6
Requires-Dist: caldav
Requires-Dist: ics
Requires-Dist: odoo (<14.1dev,>=14.0a)
Requires-Dist: pytz
Requires-Dist: requests
